{"3":{"title":"Infiltrator.jl","pagetitle":"Infiltrator.jl","ref":"/inf/stable/#Infiltrator.jl"},"4":{"title":"@infiltrate","pagetitle":"Infiltrator.jl","ref":"/inf/stable/#@infiltrate"},"5":{"title":"@exfiltrate","pagetitle":"Infiltrator.jl","ref":"/inf/stable/#@exfiltrate"},"6":{"title":"The safehouse","pagetitle":"Infiltrator.jl","ref":"/inf/stable/#The-safehouse"},"7":{"title":"Example usage","pagetitle":"Infiltrator.jl","ref":"/inf/stable/#Example-usage"},"8":{"title":"Related projects","pagetitle":"Infiltrator.jl","ref":"/inf/stable/#Related-projects"},"11":{"title":"API","pagetitle":"API","ref":"/inf/stable/API/#API"},"12":{"title":"Infiltration and exfiltration","pagetitle":"API","ref":"/inf/stable/API/#Infiltration-and-exfiltration"},"13":{"title":"Infiltrator.@infiltrate","pagetitle":"API","ref":"/inf/stable/API/#Infiltrator.@infiltrate"},"14":{"title":"Infiltrator.infiltrate","pagetitle":"API","ref":"/inf/stable/API/#Infiltrator.infiltrate"},"15":{"title":"Infiltrator.@exfiltrate","pagetitle":"API","ref":"/inf/stable/API/#Infiltrator.@exfiltrate"},"16":{"title":"The safehouse","pagetitle":"API","ref":"/inf/stable/API/#The-safehouse"},"17":{"title":"Infiltrator.safehouse","pagetitle":"API","ref":"/inf/stable/API/#Infiltrator.safehouse"},"18":{"title":"Infiltrator.clear_store!","pagetitle":"API","ref":"/inf/stable/API/#Infiltrator.clear_store!"},"19":{"title":"Infiltrator.set_store!","pagetitle":"API","ref":"/inf/stable/API/#Infiltrator.set_store!"},"20":{"title":"Infiltrator.@withstore","pagetitle":"API","ref":"/inf/stable/API/#Infiltrator.@withstore"},"21":{"title":"Utility","pagetitle":"API","ref":"/inf/stable/API/#Utility"},"22":{"title":"Infiltrator.clear_disabled!","pagetitle":"API","ref":"/inf/stable/API/#Infiltrator.clear_disabled!"},"23":{"title":"Infiltrator.end_session!","pagetitle":"API","ref":"/inf/stable/API/#Infiltrator.end_session!"},"24":{"title":"Infiltrator.toggle_async_check","pagetitle":"API","ref":"/inf/stable/API/#Infiltrator.toggle_async_check"},"28":{"title":"JuliaInterpreter","pagetitle":"Home","ref":"/debug/stable/#JuliaInterpreter"},"29":{"title":"Use as an interpreter","pagetitle":"Home","ref":"/debug/stable/#Use-as-an-interpreter"},"30":{"title":"Breakpoints","pagetitle":"Home","ref":"/debug/stable/#Breakpoints"},"31":{"title":"debug_command","pagetitle":"Home","ref":"/debug/stable/#debug_command"},"32":{"title":"Hooks","pagetitle":"Home","ref":"/debug/stable/#Hooks"},"35":{"title":"Lowered representation","pagetitle":"Lowered representation","ref":"/debug/stable/ast/#Lowered-representation"},"38":{"title":"Function reference","pagetitle":"Function reference","ref":"/debug/stable/dev_reference/#Function-reference"},"39":{"title":"Running the interpreter","pagetitle":"Function reference","ref":"/debug/stable/dev_reference/#Running-the-interpreter"},"40":{"title":"JuliaInterpreter.@interpret","pagetitle":"Function reference","ref":"/debug/stable/dev_reference/#JuliaInterpreter.@interpret"},"41":{"title":"Frame creation","pagetitle":"Function reference","ref":"/debug/stable/dev_reference/#Frame-creation"},"42":{"title":"JuliaInterpreter.Frame","pagetitle":"Function reference","ref":"/debug/stable/dev_reference/#JuliaInterpreter.Frame-Tuple{Module, Expr}"},"43":{"title":"JuliaInterpreter.ExprSplitter","pagetitle":"Function reference","ref":"/debug/stable/dev_reference/#JuliaInterpreter.ExprSplitter"},"44":{"title":"JuliaInterpreter.enter_call","pagetitle":"Function reference","ref":"/debug/stable/dev_reference/#JuliaInterpreter.enter_call"},"45":{"title":"JuliaInterpreter.enter_call_expr","pagetitle":"Function reference","ref":"/debug/stable/dev_reference/#JuliaInterpreter.enter_call_expr"},"46":{"title":"JuliaInterpreter.prepare_frame","pagetitle":"Function reference","ref":"/debug/stable/dev_reference/#JuliaInterpreter.prepare_frame"},"47":{"title":"JuliaInterpreter.determine_method_for_expr","pagetitle":"Function reference","ref":"/debug/stable/dev_reference/#JuliaInterpreter.determine_method_for_expr"},"48":{"title":"JuliaInterpreter.prepare_args","pagetitle":"Function reference","ref":"/debug/stable/dev_reference/#JuliaInterpreter.prepare_args"},"49":{"title":"JuliaInterpreter.prepare_call","pagetitle":"Function reference","ref":"/debug/stable/dev_reference/#JuliaInterpreter.prepare_call"},"50":{"title":"JuliaInterpreter.get_call_framecode","pagetitle":"Function reference","ref":"/debug/stable/dev_reference/#JuliaInterpreter.get_call_framecode"},"51":{"title":"JuliaInterpreter.optimize!","pagetitle":"Function reference","ref":"/debug/stable/dev_reference/#JuliaInterpreter.optimize!"},"52":{"title":"Frame traversal","pagetitle":"Function reference","ref":"/debug/stable/dev_reference/#Frame-traversal"},"53":{"title":"JuliaInterpreter.root","pagetitle":"Function reference","ref":"/debug/stable/dev_reference/#JuliaInterpreter.root"},"54":{"title":"JuliaInterpreter.leaf","pagetitle":"Function reference","ref":"/debug/stable/dev_reference/#JuliaInterpreter.leaf"},"55":{"title":"Frame execution","pagetitle":"Function reference","ref":"/debug/stable/dev_reference/#Frame-execution"},"56":{"title":"JuliaInterpreter.Compiled","pagetitle":"Function reference","ref":"/debug/stable/dev_reference/#JuliaInterpreter.Compiled"},"57":{"title":"JuliaInterpreter.step_expr!","pagetitle":"Function reference","ref":"/debug/stable/dev_reference/#JuliaInterpreter.step_expr!"},"58":{"title":"JuliaInterpreter.finish!","pagetitle":"Function reference","ref":"/debug/stable/dev_reference/#JuliaInterpreter.finish!"},"59":{"title":"JuliaInterpreter.finish_and_return!","pagetitle":"Function reference","ref":"/debug/stable/dev_reference/#JuliaInterpreter.finish_and_return!"},"60":{"title":"JuliaInterpreter.finish_stack!","pagetitle":"Function reference","ref":"/debug/stable/dev_reference/#JuliaInterpreter.finish_stack!"},"61":{"title":"JuliaInterpreter.get_return","pagetitle":"Function reference","ref":"/debug/stable/dev_reference/#JuliaInterpreter.get_return"},"62":{"title":"JuliaInterpreter.next_until!","pagetitle":"Function reference","ref":"/debug/stable/dev_reference/#JuliaInterpreter.next_until!"},"63":{"title":"JuliaInterpreter.maybe_next_until!","pagetitle":"Function reference","ref":"/debug/stable/dev_reference/#JuliaInterpreter.maybe_next_until!"},"64":{"title":"JuliaInterpreter.through_methoddef_or_done!","pagetitle":"Function reference","ref":"/debug/stable/dev_reference/#JuliaInterpreter.through_methoddef_or_done!"},"65":{"title":"JuliaInterpreter.evaluate_call!","pagetitle":"Function reference","ref":"/debug/stable/dev_reference/#JuliaInterpreter.evaluate_call!"},"66":{"title":"JuliaInterpreter.evaluate_foreigncall","pagetitle":"Function reference","ref":"/debug/stable/dev_reference/#JuliaInterpreter.evaluate_foreigncall"},"67":{"title":"JuliaInterpreter.maybe_evaluate_builtin","pagetitle":"Function reference","ref":"/debug/stable/dev_reference/#JuliaInterpreter.maybe_evaluate_builtin"},"68":{"title":"JuliaInterpreter.next_call!","pagetitle":"Function reference","ref":"/debug/stable/dev_reference/#JuliaInterpreter.next_call!"},"69":{"title":"JuliaInterpreter.maybe_next_call!","pagetitle":"Function reference","ref":"/debug/stable/dev_reference/#JuliaInterpreter.maybe_next_call!"},"70":{"title":"JuliaInterpreter.next_line!","pagetitle":"Function reference","ref":"/debug/stable/dev_reference/#JuliaInterpreter.next_line!"},"71":{"title":"JuliaInterpreter.until_line!","pagetitle":"Function reference","ref":"/debug/stable/dev_reference/#JuliaInterpreter.until_line!"},"72":{"title":"JuliaInterpreter.maybe_reset_frame!","pagetitle":"Function reference","ref":"/debug/stable/dev_reference/#JuliaInterpreter.maybe_reset_frame!"},"73":{"title":"JuliaInterpreter.maybe_step_through_wrapper!","pagetitle":"Function reference","ref":"/debug/stable/dev_reference/#JuliaInterpreter.maybe_step_through_wrapper!"},"74":{"title":"JuliaInterpreter.maybe_step_through_kwprep!","pagetitle":"Function reference","ref":"/debug/stable/dev_reference/#JuliaInterpreter.maybe_step_through_kwprep!"},"75":{"title":"JuliaInterpreter.handle_err","pagetitle":"Function reference","ref":"/debug/stable/dev_reference/#JuliaInterpreter.handle_err"},"76":{"title":"JuliaInterpreter.debug_command","pagetitle":"Function reference","ref":"/debug/stable/dev_reference/#JuliaInterpreter.debug_command"},"77":{"title":"Breakpoints","pagetitle":"Function reference","ref":"/debug/stable/dev_reference/#Breakpoints"},"78":{"title":"JuliaInterpreter.@breakpoint","pagetitle":"Function reference","ref":"/debug/stable/dev_reference/#JuliaInterpreter.@breakpoint"},"79":{"title":"JuliaInterpreter.@bp","pagetitle":"Function reference","ref":"/debug/stable/dev_reference/#JuliaInterpreter.@bp"},"80":{"title":"JuliaInterpreter.breakpoint","pagetitle":"Function reference","ref":"/debug/stable/dev_reference/#JuliaInterpreter.breakpoint"},"81":{"title":"JuliaInterpreter.enable","pagetitle":"Function reference","ref":"/debug/stable/dev_reference/#JuliaInterpreter.enable"},"82":{"title":"JuliaInterpreter.disable","pagetitle":"Function reference","ref":"/debug/stable/dev_reference/#JuliaInterpreter.disable"},"83":{"title":"JuliaInterpreter.remove","pagetitle":"Function reference","ref":"/debug/stable/dev_reference/#JuliaInterpreter.remove"},"84":{"title":"JuliaInterpreter.toggle","pagetitle":"Function reference","ref":"/debug/stable/dev_reference/#JuliaInterpreter.toggle"},"85":{"title":"JuliaInterpreter.break_on","pagetitle":"Function reference","ref":"/debug/stable/dev_reference/#JuliaInterpreter.break_on"},"86":{"title":"JuliaInterpreter.break_off","pagetitle":"Function reference","ref":"/debug/stable/dev_reference/#JuliaInterpreter.break_off"},"87":{"title":"JuliaInterpreter.breakpoints","pagetitle":"Function reference","ref":"/debug/stable/dev_reference/#JuliaInterpreter.breakpoints"},"88":{"title":"JuliaInterpreter.dummy_breakpoint","pagetitle":"Function reference","ref":"/debug/stable/dev_reference/#JuliaInterpreter.dummy_breakpoint"},"89":{"title":"Types","pagetitle":"Function reference","ref":"/debug/stable/dev_reference/#Types"},"90":{"title":"JuliaInterpreter.Frame","pagetitle":"Function reference","ref":"/debug/stable/dev_reference/#JuliaInterpreter.Frame"},"91":{"title":"JuliaInterpreter.FrameCode","pagetitle":"Function reference","ref":"/debug/stable/dev_reference/#JuliaInterpreter.FrameCode"},"92":{"title":"JuliaInterpreter.FrameData","pagetitle":"Function reference","ref":"/debug/stable/dev_reference/#JuliaInterpreter.FrameData"},"93":{"title":"JuliaInterpreter._INACTIVE_EXCEPTION","pagetitle":"Function reference","ref":"/debug/stable/dev_reference/#JuliaInterpreter._INACTIVE_EXCEPTION"},"94":{"title":"JuliaInterpreter.FrameInstance","pagetitle":"Function reference","ref":"/debug/stable/dev_reference/#JuliaInterpreter.FrameInstance"},"95":{"title":"JuliaInterpreter.BreakpointState","pagetitle":"Function reference","ref":"/debug/stable/dev_reference/#JuliaInterpreter.BreakpointState"},"96":{"title":"JuliaInterpreter.BreakpointRef","pagetitle":"Function reference","ref":"/debug/stable/dev_reference/#JuliaInterpreter.BreakpointRef"},"97":{"title":"JuliaInterpreter.AbstractBreakpoint","pagetitle":"Function reference","ref":"/debug/stable/dev_reference/#JuliaInterpreter.AbstractBreakpoint"},"98":{"title":"JuliaInterpreter.BreakpointSignature","pagetitle":"Function reference","ref":"/debug/stable/dev_reference/#JuliaInterpreter.BreakpointSignature"},"99":{"title":"JuliaInterpreter.BreakpointFileLocation","pagetitle":"Function reference","ref":"/debug/stable/dev_reference/#JuliaInterpreter.BreakpointFileLocation"},"100":{"title":"Internal storage","pagetitle":"Function reference","ref":"/debug/stable/dev_reference/#Internal-storage"},"101":{"title":"JuliaInterpreter.framedict","pagetitle":"Function reference","ref":"/debug/stable/dev_reference/#JuliaInterpreter.framedict"},"102":{"title":"JuliaInterpreter.genframedict","pagetitle":"Function reference","ref":"/debug/stable/dev_reference/#JuliaInterpreter.genframedict"},"103":{"title":"JuliaInterpreter.compiled_methods","pagetitle":"Function reference","ref":"/debug/stable/dev_reference/#JuliaInterpreter.compiled_methods"},"104":{"title":"JuliaInterpreter.compiled_modules","pagetitle":"Function reference","ref":"/debug/stable/dev_reference/#JuliaInterpreter.compiled_modules"},"105":{"title":"JuliaInterpreter.interpreted_methods","pagetitle":"Function reference","ref":"/debug/stable/dev_reference/#JuliaInterpreter.interpreted_methods"},"106":{"title":"Utilities","pagetitle":"Function reference","ref":"/debug/stable/dev_reference/#Utilities"},"107":{"title":"JuliaInterpreter.eval_code","pagetitle":"Function reference","ref":"/debug/stable/dev_reference/#JuliaInterpreter.eval_code"},"108":{"title":"JuliaInterpreter.@lookup","pagetitle":"Function reference","ref":"/debug/stable/dev_reference/#JuliaInterpreter.@lookup"},"109":{"title":"JuliaInterpreter.is_wrapper_call","pagetitle":"Function reference","ref":"/debug/stable/dev_reference/#JuliaInterpreter.is_wrapper_call"},"110":{"title":"JuliaInterpreter.is_doc_expr","pagetitle":"Function reference","ref":"/debug/stable/dev_reference/#JuliaInterpreter.is_doc_expr"},"111":{"title":"JuliaInterpreter.is_global_ref","pagetitle":"Function reference","ref":"/debug/stable/dev_reference/#JuliaInterpreter.is_global_ref"},"112":{"title":"CodeTracking.whereis","pagetitle":"Function reference","ref":"/debug/stable/dev_reference/#CodeTracking.whereis"},"113":{"title":"JuliaInterpreter.linenumber","pagetitle":"Function reference","ref":"/debug/stable/dev_reference/#JuliaInterpreter.linenumber"},"114":{"title":"JuliaInterpreter.Variable","pagetitle":"Function reference","ref":"/debug/stable/dev_reference/#JuliaInterpreter.Variable"},"115":{"title":"JuliaInterpreter.locals","pagetitle":"Function reference","ref":"/debug/stable/dev_reference/#JuliaInterpreter.locals"},"116":{"title":"JuliaInterpreter.whichtt","pagetitle":"Function reference","ref":"/debug/stable/dev_reference/#JuliaInterpreter.whichtt"},"117":{"title":"Hooks","pagetitle":"Function reference","ref":"/debug/stable/dev_reference/#Hooks"},"118":{"title":"JuliaInterpreter.on_breakpoints_updated","pagetitle":"Function reference","ref":"/debug/stable/dev_reference/#JuliaInterpreter.on_breakpoints_updated"},"119":{"title":"JuliaInterpreter.firehooks","pagetitle":"Function reference","ref":"/debug/stable/dev_reference/#JuliaInterpreter.firehooks"},"122":{"title":"Internals","pagetitle":"Internals","ref":"/debug/stable/internals/#Internals"},"123":{"title":"Basic usage","pagetitle":"Internals","ref":"/debug/stable/internals/#Basic-usage"},"124":{"title":"More complex expressions","pagetitle":"Internals","ref":"/debug/stable/internals/#More-complex-expressions"},"125":{"title":"Toplevel code and world age","pagetitle":"Internals","ref":"/debug/stable/internals/#Toplevel-code-and-world-age"}}